django_aps/__init__.py
django_aps/admin.py
django_aps/apps.py
django_aps/base.py
django_aps/models.py
django_aps/settings.py
django_aps/tests.py
django_aps/urls.py
django_aps/migrations/0001_initial.py
django_aps/migrations/__init__.py
django_aps/model/__init__.py
django_aps/model/aps_models.py
django_aps/model/trigger_models.py
django_aps/repository/__init__.py
django_aps/repository/apscheduler_func_model_mapper.py
django_aps/repository/apscheduler_job_model_mapper.py
django_aps/serializers/__init__.py
django_aps/serializers/apscheduler_serializers.py
django_aps/service/__init__.py
django_aps/service/discover_service.py
django_aps/service/scheduler_service.py
django_aps/utils/__init__.py
django_aps/utils/common.py
django_aps/utils/discover.py
django_aps/utils/register.py
django_aps/views/__init__.py
django_aps/views/apscheduler_view.py
django_aps-0.1.1.dist-info/METADATA
django_aps-0.1.1.dist-info/WHEEL
django_aps-0.1.1.dist-info/top_level.txt
django_aps-0.1.1.dist-info/RECORD
